AUTHORS.rst
CONTRIBUTING.rst
HISTORY.rst
LICENSE
MANIFEST.in
README.rst
setup.cfg
setup.py
docs/Makefile
docs/authors.rst
docs/conf.py
docs/contributing.rst
docs/history.rst
docs/index.rst
docs/installation.rst
docs/make.bat
docs/not_implemented.rst
docs/readme.rst
docs/usage.rst
docs/_build/html/_static/ajax-loader.gif
docs/_build/html/_static/comment-bright.png
docs/_build/html/_static/comment-close.png
docs/_build/html/_static/comment.png
docs/_build/html/_static/down-pressed.png
docs/_build/html/_static/down.png
docs/_build/html/_static/file.png
docs/_build/html/_static/minus.png
docs/_build/html/_static/plus.png
docs/_build/html/_static/up-pressed.png
docs/_build/html/_static/up.png
docs/api/index.rst
docs/api/simple_zpl2.printer.rst
docs/api/simple_zpl2.zpl_document.rst
simple_zpl2/__init__.py
simple_zpl2/printer.py
simple_zpl2/zpl_document.py
simple_zpl2.egg-info/PKG-INFO
simple_zpl2.egg-info/SOURCES.txt
simple_zpl2.egg-info/dependency_links.txt
simple_zpl2.egg-info/entry_points.txt
simple_zpl2.egg-info/not-zip-safe
simple_zpl2.egg-info/requires.txt
simple_zpl2.egg-info/top_level.txt
tests/__init__.py
tests/scratchpad.py
tests/test_simple_zpl2.py
tests/test_zpl_a.py
tests/test_zpl_b0.py
tests/test_zpl_b1.py
tests/test_zpl_b2.py
tests/test_zpl_b3.py
tests/test_zpl_b4.py
tests/test_zpl_b5.py
tests/test_zpl_b7.py
tests/test_zpl_b8.py
tests/test_zpl_b9.py
tests/test_zpl_ba.py
tests/test_zpl_bb.py
tests/test_zpl_bc.py
tests/test_zpl_bd.py
tests/test_zpl_be.py
tests/test_zpl_bf.py
tests/test_zpl_bi.py
tests/test_zpl_bj.py
tests/test_zpl_bk.py
tests/test_zpl_bl.py
tests/test_zpl_bm.py
tests/test_zpl_bo.py
tests/test_zpl_bp.py
tests/test_zpl_bq.py
tests/test_zpl_br.py
tests/test_zpl_bs.py
tests/test_zpl_bt.py
tests/test_zpl_bu.py
tests/test_zpl_bx.py
tests/test_zpl_by.py
tests/test_zpl_bz.py
tests/test_zpl_fb.py
tests/test_zpl_fd.py
tests/test_zpl_fo.py
tests/test_zpl_fx.py
tests/test_zpl_gb.py
tests/test_zpl_gc.py
tests/test_zpl_lh.py
tests/test_zpl_pq.py
tests/test_zpl_sn.py
tests/test_zpl_sp.py
tests/test_zpl_tb.py
tests/test_zpl_zz.py
tests/util.py