Metadata-Version: 1.1
Name: simple-zpl2
Version: 0.2.2
Summary: For building ZPL2 strings for printing barcodes with Zebra or compatible label printers.
Home-page: https://github.com/sacherjj/simple_zpl2
Author: Joe Sacher
Author-email: sacherjj@gmail.com
License: MIT license
Keywords: simple_zpl2
Platform: UNKNOWN
Classifier: Development Status :: 3 - Alpha
Classifier: Intended Audience :: Developers
Classifier: License :: OSI Approved :: MIT License
Classifier: Natural Language :: English
Classifier: Programming Language :: Python :: 3
Classifier: Programming Language :: Python :: 3.3
Classifier: Programming Language :: Python :: 3.4
Classifier: Programming Language :: Python :: 3.5
Classifier: Programming Language :: Python :: 3.6
